mint/__init__.py
mint/cli.py
pymnt-0.1.0.dist-info/METADATA
pymnt-0.1.0.dist-info/WHEEL
pymnt-0.1.0.dist-info/entry_points.txt
pymnt-0.1.0.dist-info/top_level.txt
pymnt-0.1.0.dist-info/RECORD
